README.md
setup.py
yandex/__init__.py
yandex/errors.py
yandex/yandex.py
yandex.egg-info/PKG-INFO
yandex.egg-info/SOURCES.txt
yandex.egg-info/dependency_links.txt
yandex.egg-info/requires.txt
yandex.egg-info/top_level.txt