Metadata-Version: 1.1
Name: yandex
Version: 0.0.2
Summary:  A python wrapper around the Yandex API 
Home-page: https://www.github.com/Dogeek/yandex
Author: Dogeek
Author-email: UNKNOWN
License: MIT
Download-URL: https://www.github.com/Dogeek/yandex/releases
Platform: UNKNOWN
Classifier: Programming Language :: Python :: 3
Classifier: License :: OSI Approved :: MIT License
